legame/__init__.py
legame/board_game.py
legame/callout.py
legame/configurable.py
legame/exit_states.py
legame/flipper.py
legame/game.py
legame/joiner.py
legame/neighbors.py
legame/network_game.py
legame/resources.py
legame/sprite_enhancement.py
legame/examples/__init__.py
legame/examples/alien-herd.py
legame/examples/board-game.py
legame/examples/herd.py
legame/examples/network-game.py
legame/examples/seeking-demo.py
legame/examples/steering-demo.py
legame/examples/resources/images/bye-bye.png
legame/examples/resources/images/game-over.png
legame/examples/resources/images/test.svg
legame/examples/resources/images/you-win.png
legame/examples/resources/images/Block/b/00.png
legame/examples/resources/images/Block/b/enter/00.png
legame/examples/resources/images/Block/b/enter/01.png
legame/examples/resources/images/Block/b/enter/02.png
legame/examples/resources/images/Block/b/jiggle/00.png
legame/examples/resources/images/Block/b/jiggle/01.png
legame/examples/resources/images/Block/b/jiggle/02.png
legame/examples/resources/images/Block/g/00.png
legame/examples/resources/images/Block/g/enter/00.png
legame/examples/resources/images/Block/g/enter/01.png
legame/examples/resources/images/Block/g/enter/02.png
legame/examples/resources/images/Block/g/jiggle/00.png
legame/examples/resources/images/Block/g/jiggle/01.png
legame/examples/resources/images/Block/g/jiggle/02.png
legame/examples/resources/images/Block/r/00.png
legame/examples/resources/images/Block/r/enter/00.png
legame/examples/resources/images/Block/r/enter/01.png
legame/examples/resources/images/Block/r/enter/02.png
legame/examples/resources/images/Block/r/jiggle/00.png
legame/examples/resources/images/Block/r/jiggle/01.png
legame/examples/resources/images/Block/r/jiggle/02.png
legame/examples/resources/images/Glow/00.png
legame/examples/resources/images/Glow/01.png
legame/examples/resources/images/Glow/02.png
legame/examples/resources/images/Glow/03.png
legame/examples/resources/images/Glow/04.png
legame-1.0.2.dist-info/LICENSE
legame-1.0.2.dist-info/WHEEL
legame-1.0.2.dist-info/METADATA
legame-1.0.2.dist-info/RECORD
