Metadata-Version: 2.1
Name: legame
Version: 1.0.2
Summary: Modules which aid in creating 2-dimensional games with pygame.
Author-email: Leon Dionne <ldionne@dridesign.sh.cn>
Classifier: License :: OSI Approved :: GNU General Public License v3 or later (GPLv3+)
Requires-Dist: pygame
Requires-Dist: appdirs
Requires-Dist: pytest
Requires-Dist: cable_car
Project-URL: Home, https://github.com/Zen-Master-SoSo/legame
